prstools/__init__.py
prstools/_cmd.py
prstools/_ext_utils.py
prstools/_modidx.py
prstools/_parser_vars.py
prstools/loaders.py
prstools/parse_genet.py
prstools/scores.py
prstools/utils.py
prstools/data/__init__.py
prstools/data/_example/__init__.py
prstools/data/_example/sumstats.tsv
prstools/data/_example/target.bed
prstools/data/_example/target.bim
prstools/data/_example/target.fam
prstools/data/_example/ldgm_1kg_pop/__init__.py
prstools/data/_example/ldgm_1kg_pop/EUR/1kg_chr22_22004675_23374984.EUR.edgelist
prstools/data/_example/ldgm_1kg_pop/EUR/1kg_chr22_30667654_32269392.EUR.edgelist
prstools/data/_example/ldgm_1kg_pop/EUR/__init__.py
prstools/data/_example/ldgm_1kg_pop/snplist/1kg_chr22_22004675_23374984.snplist
prstools/data/_example/ldgm_1kg_pop/snplist/1kg_chr22_30667654_32269392.snplist
prstools/data/_example/ldgm_1kg_pop/snplist/__init__.py
prstools/data/_example/ldref_1kg_pop/__init__.py
prstools/data/_example/ldref_1kg_pop/ldblk_1kg_chr22.hdf5
prstools/data/_example/ldref_1kg_pop/snpinfo_1kg_hm3
prstools/data/defs/__init__.py
prstools/data/defs/regdef/__init__.py
prstools/data/defs/regdef/regions_1blk_shift=0.regdef.tsv
prstools/data/defs/regdef/regions_2blk_shift=0.regdef.tsv
prstools/data/defs/regdef/regions_2blk_shift=1.regdef.tsv
prstools/data/defs/regdef/regions_3blk_shift=0.regdef.tsv
prstools/data/defs/regdef/regions_3blk_shift=1.regdef.tsv
prstools/data/defs/regdef/regions_3blk_shift=2.regdef.tsv
prstools/models/__init__.py
prstools/models/_base.py
prstools/models/_compute.py
prstools/tests/__init__.py
prstools/tests/test_cli_model_examples.py
prstools-0.0.58.dist-info/LICENSE
prstools-0.0.58.dist-info/METADATA
prstools-0.0.58.dist-info/WHEEL
prstools-0.0.58.dist-info/entry_points.txt
prstools-0.0.58.dist-info/top_level.txt
prstools-0.0.58.dist-info/RECORD
