Metadata-Version: 2.1
Name: prstools
Version: 0.0.58
Summary: Convenient and powerfull Polygenic Risk Score creation.
Home-page: https://github.com/mennojw/prstools-release
Author: Menno Witteveen et al.
Author-email: menno102@hotmail.com
License: MIT License
Keywords: PRS PGS polygenic genomics prediction genetics
Classifier: Development Status :: 4 - Beta
Classifier: Intended Audience :: Science/Research
Classifier: Natural Language :: English
Classifier: Programming Language :: Python :: 3.8
Classifier: Programming Language :: Python :: 3.9
Classifier: Programming Language :: Python :: 3.10
Classifier: Programming Language :: Python :: 3.11
Classifier: License :: OSI Approved :: MIT License
Requires-Python: >=3.8
License-File: LICENSE
Requires-Dist: pandas
Requires-Dist: scipy
Requires-Dist: tqdm
Requires-Dist: h5py
Requires-Dist: ipython
Requires-Dist: matplotlib
Requires-Dist: joblib
Requires-Dist: pyarrow
Requires-Dist: bed-reader<1.0; python_version < "3.9"
Requires-Dist: bed-reader; python_version >= "3.9"
Provides-Extra: dev
Requires-Dist: nbdev; extra == "dev"
Provides-Extra: full
Requires-Dist: mjwt; extra == "full"
Requires-Dist: pysnptools; extra == "full"
Requires-Dist: seaborn; extra == "full"
